processor/DataMem.vhdl
library IEEE;
use IEEE.STD_LOGIC_1164.ALL;
use IEEE.NUMERIC_STD.ALL;

entity DataMem is
    Port (
        clk : in STD_LOGIC;
        addr : in STD_LOGIC_VECTOR(7 downto 0);
        data_in : in STD_LOGIC_VECTOR(7 downto 0);
        data_out : out STD_LOGIC_VECTOR(7 downto 0);
        wr_en : in STD_LOGIC
    );
end DataMem;

architecture Behavioral of DataMem is
    type mem_type is array (0 to 255) of STD_LOGIC_VECTOR(7 downto 0);
    signal memory : mem_type := (others => (others => '0'));
begin
    process(clk)
    begin
        if rising_edge(clk) then
            if wr_en = '1' then
                memory(to_integer(unsigned(addr))) <= data_in;
            end if;
            data_out <= memory(to_integer(unsigned(addr)));
        end if;
    end process;
end Behavioral;

processor/InstrMem.vhdl
library IEEE;
use IEEE.STD_LOGIC_1164.ALL;
use IEEE.NUMERIC_STD.ALL;

entity InstrMem is
    Port (
        clk : in STD_LOGIC;
        addr : in STD_LOGIC_VECTOR(7 downto 0);
        instr : out STD_LOGIC_VECTOR(31 downto 0)
    );
end InstrMem;

architecture Behavioral of InstrMem is
    type mem_type is array (0 to 255) of STD_LOGIC_VECTOR(31 downto 0);
    signal memory : mem_type := (
        -- Example program
        0 => "00000000000000110000001000000000",  -- ADD R3, R2
        1 => "00100000000001000000001100000000",  -- SUB R4, R3
        2 => "01000000000001010000010000000000",  -- AND R5, R4
        3 => "01100000000001100000010100000000",  -- OR  R6, R5
        4 => "10000000000001110000011000000000",  -- XOR R7, R6
        5 => "10100000000010000000011100000000",  -- NOR R8, R7
        others => (others => '0')
    );
begin
    process(clk)
    begin
        if rising_edge(clk) then
            instr <= memory(to_integer(unsigned(addr)));
        end if;
    end process;
end Behavioral;

processor/ALU.vhdl
library IEEE;
use IEEE.STD_LOGIC_1164.ALL;
use IEEE.NUMERIC_STD.ALL; -- For arithmetic operations

entity ALU is
    Port (
        A : in STD_LOGIC_VECTOR (7 downto 0);  -- 8-bit input A
        B : in STD_LOGIC_VECTOR (7 downto 0);  -- 8-bit input B
        sel : in STD_LOGIC_VECTOR (2 downto 0); -- 3-bit select input
        Result : out STD_LOGIC_VECTOR (7 downto 0); -- 8-bit output Result
        Zero : out STD_LOGIC                 -- Zero flag
    );
end ALU;

architecture Behavioral of ALU is
begin
    process(A, B, sel)
    variable temp_result : STD_LOGIC_VECTOR (7 downto 0);
    begin
        case sel is
            when "000" => -- ADD
                temp_result := std_logic_vector(signed(A) + signed(B));
            when "001" => -- SUBTRACT
                temp_result := std_logic_vector(signed(A) - signed(B));
            when "010" => -- AND
                temp_result := A and B;
            when "011" => -- OR
                temp_result := A or B;
            when "100" => -- XOR
                temp_result := A xor B;
            when "101" => -- NOR
                temp_result := not (A or B);
            when others =>
                temp_result := (others => '0');  -- Default case
        end case;

        Result <= temp_result; -- Assign result to output
        
        -- Set the Zero flag
        if temp_result = "00000000" then
            Zero <= '1';
        else
            Zero <= '0';
        end if;
    end process;
end Behavioral;

processor/Processor.vhdl
library IEEE;
use IEEE.STD_LOGIC_1164.ALL;
use ieee.numeric_std.all;

entity Processor is
    Port (
        clk : in STD_LOGIC;
        reset : in STD_LOGIC;
        
        -- Instruction Memory Interface
        instr_addr : out STD_LOGIC_VECTOR (7 downto 0);
        instr : in STD_LOGIC_VECTOR (31 downto 0);
        
        -- Data Memory Interface
        data_addr : out STD_LOGIC_VECTOR (7 downto 0);
        data_in : out STD_LOGIC_VECTOR (7 downto 0);
        data_out : in STD_LOGIC_VECTOR (7 downto 0);
        data_wr : out STD_LOGIC
    );
end Processor;

architecture Behavioral of Processor is
    -- Components
    component ALU
        Port (
            A : in STD_LOGIC_VECTOR (7 downto 0);
            B : in STD_LOGIC_VECTOR (7 downto 0);
            sel : in STD_LOGIC_VECTOR (2 downto 0);
            Result : out STD_LOGIC_VECTOR (7 downto 0);
            Zero : out STD_LOGIC
        );
    end component;

    -- Processor Signals
    signal PC : STD_LOGIC_VECTOR (7 downto 0) := (others => '0');
    signal Inst_Reg : STD_LOGIC_VECTOR (31 downto 0);
    signal Reg_A, Reg_B : STD_LOGIC_VECTOR (7 downto 0);
    signal ALU_Res : STD_LOGIC_VECTOR (7 downto 0);
    signal ALU_Ctrl : STD_LOGIC_VECTOR (2 downto 0);
    signal Zero_Flag : STD_LOGIC;

begin
    -- Instruction Fetch
    instr_addr <= PC;
    Inst_Reg <= instr;

    -- Instruction Decode
    process(Inst_Reg)
    begin
        case Inst_Reg(31 downto 29) is
            when "000" => ALU_Ctrl <= "000"; -- ADD
            when "001" => ALU_Ctrl <= "001"; -- SUB
            when "010" => ALU_Ctrl <= "010"; -- AND
            when "011" => ALU_Ctrl <= "011"; -- OR
            when "100" => ALU_Ctrl <= "100"; -- XOR
            when "101" => ALU_Ctrl <= "101"; -- NOR
            when others => ALU_Ctrl <= "111"; -- Invalid
        end case;

        Reg_A <= Inst_Reg(23 downto 16);
        Reg_B <= Inst_Reg(15 downto 8);
    end process;

    -- ALU Execution
    ALU_Unit: ALU
        port map (
            A => Reg_A,
            B => Reg_B,
            sel => ALU_Ctrl,
            Result => ALU_Res,
            Zero => Zero_Flag
        );

    -- Memory Access
    data_addr <= ALU_Res(7 downto 0);
    data_in <= Reg_B;
    data_wr <= '1' when ALU_Ctrl = "000" else '0'; -- Write for ADD only

    -- Program Counter Update
    process(clk, reset)
    begin
        if reset = '1' then
            PC <= (others => '0');
        elsif rising_edge(clk) then
            PC <= std_logic_vector(unsigned(PC) + 1);
        end if;
    end process;

end Behavioral;

processor/Top.vhdl
library IEEE;
use IEEE.STD_LOGIC_1164.ALL;

entity Top is
    Port (
        clk : in STD_LOGIC;
        reset : in STD_LOGIC
    );
end Top;

architecture Behavioral of Top is
    -- Component declarations
    component Processor is
        Port (
            clk : in STD_LOGIC;
            reset : in STD_LOGIC;
            instr_addr : out STD_LOGIC_VECTOR(7 downto 0);
            instr : in STD_LOGIC_VECTOR(31 downto 0);
            data_addr : out STD_LOGIC_VECTOR(7 downto 0);
            data_in : out STD_LOGIC_VECTOR(7 downto 0);
            data_out : in STD_LOGIC_VECTOR(7 downto 0);
            data_wr : out STD_LOGIC
        );
    end component;

    component InstrMem is
        Port (
            clk : in STD_LOGIC;
            addr : in STD_LOGIC_VECTOR(7 downto 0);
            instr : out STD_LOGIC_VECTOR(31 downto 0)
        );
    end component;

    component DataMem is
        Port (
            clk : in STD_LOGIC;
            addr : in STD_LOGIC_VECTOR(7 downto 0);
            data_in : in STD_LOGIC_VECTOR(7 downto 0);
            data_out : out STD_LOGIC_VECTOR(7 downto 0);
            wr_en : in STD_LOGIC
        );
    end component;

    -- Internal signals
    signal instr_addr : STD_LOGIC_VECTOR(7 downto 0);
    signal instruction : STD_LOGIC_VECTOR(31 downto 0);
    signal data_addr : STD_LOGIC_VECTOR(7 downto 0);
    signal data_to_mem : STD_LOGIC_VECTOR(7 downto 0);
    signal data_from_mem : STD_LOGIC_VECTOR(7 downto 0);
    signal data_wr : STD_LOGIC;

begin
    -- Processor instantiation
    proc: Processor
        port map (
            clk => clk,
            reset => reset,
            instr_addr => instr_addr,
            instr => instruction,
            data_addr => data_addr,
            data_in => data_to_mem,
            data_out => data_from_mem,
            data_wr => data_wr
        );

    -- Instruction Memory instantiation
    imem: InstrMem
        port map (
            clk => clk,
            addr => instr_addr,
            instr => instruction
        );

    -- Data Memory instantiation
    dmem: DataMem
        port map (
            clk => clk,
            addr => data_addr,
            data_in => data_to_mem,
            data_out => data_from_mem,
            wr_en => data_wr
        );

end Behavioral;

processor/Top_tb.vhdl
library IEEE;
use IEEE.STD_LOGIC_1164.ALL;
use IEEE.NUMERIC_STD.ALL;

entity Top_tb is
end Top_tb;

architecture Behavioral of Top_tb is
    -- Component Declaration
    component Top
        Port (
            clk : in STD_LOGIC;
            reset : in STD_LOGIC
        );
    end component;
    
    -- Test Signals
    signal clk : STD_LOGIC := '0';
    signal reset : STD_LOGIC := '0';
    
    -- Clock period definition
    constant CLK_PERIOD : time := 10 ns;
    
begin
    -- Instantiate the Unit Under Test (UUT)
    UUT: Top port map (
        clk => clk,
        reset => reset
    );
    
    -- Clock process
    clk_process: process
    begin
        clk <= '0';
        wait for CLK_PERIOD/2;
        clk <= '1';
        wait for CLK_PERIOD/2;
    end process;
    
    -- Stimulus process
    stim_proc: process
    begin
        -- Initialize with reset
        reset <= '1';
        wait for CLK_PERIOD*4;
        
        -- Release reset and let it run
        reset <= '0';
        wait for CLK_PERIOD*20;  -- Run for 20 clock cycles
        
        -- Apply reset again
        reset <= '1';
        wait for CLK_PERIOD*2;
        reset <= '0';
        
        -- Let it run some more
        wait for CLK_PERIOD*20;
        
        -- End simulation
        wait;
    end process;
end Behavioral;

processor/top_tb.vcd
$date
  Thu Nov 21 02:01:21 2024
$end
$version
  GHDL v0
$end
$timescale
  1 fs
$end
$scope module standard $end
$upscope $end
$scope module std_logic_1164 $end
$upscope $end
$scope module numeric_std $end
$upscope $end
$scope module top_tb $end
$var reg 1 ! clk $end
$var reg 1 " reset $end
$scope module uut $end
$var reg 1 # clk $end
$var reg 1 $ reset $end
$var reg 8 % instr_addr[7:0] $end
$var reg 32 & instruction[31:0] $end
$var reg 8 ' data_addr[7:0] $end
$var reg 8 ( data_to_mem[7:0] $end
$var reg 8 ) data_from_mem[7:0] $end
$var reg 1 * data_wr $end
$scope module proc $end
$var reg 1 + clk $end
$var reg 1 , reset $end
$var reg 8 - instr_addr[7:0] $end
$var reg 32 . instr[31:0] $end
$var reg 8 / data_addr[7:0] $end
$var reg 8 0 data_in[7:0] $end
$var reg 8 1 data_out[7:0] $end
$var reg 1 2 data_wr $end
$var reg 8 3 pc[7:0] $end
$var reg 32 4 inst_reg[31:0] $end
$var reg 8 5 reg_a[7:0] $end
$var reg 8 6 reg_b[7:0] $end
$var reg 8 7 alu_res[7:0] $end
$var reg 3 8 alu_ctrl[2:0] $end
$var reg 1 9 zero_flag $end
$scope module alu_unit $end
$var reg 8 : a[7:0] $end
$var reg 8 ; b[7:0] $end
$var reg 3 < sel[2:0] $end
$var reg 8 = result[7:0] $end
$var reg 1 > zero $end
$upscope $end
$upscope $end
$scope module imem $end
$var reg 1 ? clk $end
$var reg 8 @ addr[7:0] $end
$var reg 32 A instr[31:0] $end
$comment memory is not handled $end
$upscope $end
$scope module dmem $end
$var reg 1 B clk $end
$var reg 8 C addr[7:0] $end
$var reg 8 D data_in[7:0] $end
$var reg 8 E data_out[7:0] $end
$var reg 1 F wr_en $end
$comment memory is not handled $end
$upscope $end
$upscope $end
$upscope $end
$enddefinitions $end
#0
0!
1"
0#
1$
b00000000 %
bUUUUUUUUUUUUUUUUUUUUUUUUUUUUUUUU &
b00000000 '
bUUUUUUUU (
bUUUUUUUU )
0*
0+
1,
b00000000 -
bUUUUUUUUUUUUUUUUUUUUUUUUUUUUUUUU .
b00000000 /
bUUUUUUUU 0
bUUUUUUUU 1
02
b00000000 3
bUUUUUUUUUUUUUUUUUUUUUUUUUUUUUUUU 4
bUUUUUUUU 5
bUUUUUUUU 6
b00000000 7
b111 8
19
bUUUUUUUU :
bUUUUUUUU ;
b111 <
b00000000 =
1>
0?
b00000000 @
bUUUUUUUUUUUUUUUUUUUUUUUUUUUUUUUU A
0B
b00000000 C
bUUUUUUUU D
bUUUUUUUU E
0F
#5000000
1!
1#
b00000000000000110000001000000000 &
b00000101 '
b00000010 (
b00000000 )
1*
1+
b00000000000000110000001000000000 .
b00000101 /
b00000010 0
b00000000 1
12
b00000000000000110000001000000000 4
b00000011 5
b00000010 6
b00000101 7
b000 8
09
b00000011 :
b00000010 ;
b000 <
b00000101 =
0>
1?
b00000000000000110000001000000000 A
1B
b00000101 C
b00000010 D
b00000000 E
1F
#10000000
0!
0#
0+
0?
0B
#15000000
1!
1#
1+
1?
1B
#20000000
0!
0#
0+
0?
0B
#25000000
1!
1#
b00000010 )
1+
b00000010 1
1?
1B
b00000010 E
#30000000
0!
0#
0+
0?
0B
#35000000
1!
1#
1+
1?
1B
#40000000
0!
0"
0#
0$
0+
0,
0?
0B
#45000000
1!
1#
b00000001 %
1+
b00000001 -
b00000001 3
1?
b00000001 @
1B
#50000000
0!
0#
0+
0?
0B
#55000000
1!
1#
b00000010 %
b00100000000001000000001100000000 &
b00000001 '
b00000011 (
0*
1+
b00000010 -
b00100000000001000000001100000000 .
b00000001 /
b00000011 0
02
b00000010 3
b00100000000001000000001100000000 4
b00000100 5
b00000011 6
b00000001 7
b001 8
b00000100 :
b00000011 ;
b001 <
b00000001 =
1?
b00000010 @
b00100000000001000000001100000000 A
1B
b00000001 C
b00000011 D
0F
#60000000
0!
0#
0+
0?
0B
#65000000
1!
1#
b00000011 %
b01000000000001010000010000000000 &
b00000100 '
b00000100 (
b00000000 )
1+
b00000011 -
b01000000000001010000010000000000 .
b00000100 /
b00000100 0
b00000000 1
b00000011 3
b01000000000001010000010000000000 4
b00000101 5
b00000100 6
b00000100 7
b010 8
b00000101 :
b00000100 ;
b010 <
b00000100 =
1?
b00000011 @
b01000000000001010000010000000000 A
1B
b00000100 C
b00000100 D
b00000000 E
#70000000
0!
0#
0+
0?
0B
#75000000
1!
1#
b00000100 %
b01100000000001100000010100000000 &
b00000111 '
b00000101 (
1+
b00000100 -
b01100000000001100000010100000000 .
b00000111 /
b00000101 0
b00000100 3
b01100000000001100000010100000000 4
b00000110 5
b00000101 6
b00000111 7
b011 8
b00000110 :
b00000101 ;
b011 <
b00000111 =
1?
b00000100 @
b01100000000001100000010100000000 A
1B
b00000111 C
b00000101 D
#80000000
0!
0#
0+
0?
0B
#85000000
1!
1#
b00000101 %
b10000000000001110000011000000000 &
b00000001 '
b00000110 (
1+
b00000101 -
b10000000000001110000011000000000 .
b00000001 /
b00000110 0
b00000101 3
b10000000000001110000011000000000 4
b00000111 5
b00000110 6
b00000001 7
b100 8
b00000111 :
b00000110 ;
b100 <
b00000001 =
1?
b00000101 @
b10000000000001110000011000000000 A
1B
b00000001 C
b00000110 D
#90000000
0!
0#
0+
0?
0B
#95000000
1!
1#
b00000110 %
b10100000000010000000011100000000 &
b11110000 '
b00000111 (
1+
b00000110 -
b10100000000010000000011100000000 .
b11110000 /
b00000111 0
b00000110 3
b10100000000010000000011100000000 4
b00001000 5
b00000111 6
b11110000 7
b101 8
b00001000 :
b00000111 ;
b101 <
b11110000 =
1?
b00000110 @
b10100000000010000000011100000000 A
1B
b11110000 C
b00000111 D
#100000000
0!
0#
0+
0?
0B
#105000000
1!
1#
b00000111 %
b00000000000000000000000000000000 &
b00000000 '
b00000000 (
1*
1+
b00000111 -
b00000000000000000000000000000000 .
b00000000 /
b00000000 0
12
b00000111 3
b00000000000000000000000000000000 4
b00000000 5
b00000000 6
b00000000 7
b000 8
19
b00000000 :
b00000000 ;
b000 <
b00000000 =
1>
1?
b00000111 @
b00000000000000000000000000000000 A
1B
b00000000 C
b00000000 D
1F
#110000000
0!
0#
0+
0?
0B
#115000000
1!
1#
b00001000 %
1+
b00001000 -
b00001000 3
1?
b00001000 @
1B
#120000000
0!
0#
0+
0?
0B
#125000000
1!
1#
b00001001 %
1+
b00001001 -
b00001001 3
1?
b00001001 @
1B
#130000000
0!
0#
0+
0?
0B
#135000000
1!
1#
b00001010 %
1+
b00001010 -
b00001010 3
1?
b00001010 @
1B
#140000000
0!
0#
0+
0?
0B
#145000000
1!
1#
b00001011 %
1+
b00001011 -
b00001011 3
1?
b00001011 @
1B
#150000000
0!
0#
0+
0?
0B
#155000000
1!
1#
b00001100 %
1+
b00001100 -
b00001100 3
1?
b00001100 @
1B
#160000000
0!
0#
0+
0?
0B
#165000000
1!
1#
b00001101 %
1+
b00001101 -
b00001101 3
1?
b00001101 @
1B
#170000000
0!
0#
0+
0?
0B
#175000000
1!
1#
b00001110 %
1+
b00001110 -
b00001110 3
1?
b00001110 @
1B
#180000000
0!
0#
0+
0?
0B
#185000000
1!
1#
b00001111 %
1+
b00001111 -
b00001111 3
1?
b00001111 @
1B
#190000000
0!
0#
0+
0?
0B
#195000000
1!
1#
b00010000 %
1+
b00010000 -
b00010000 3
1?
b00010000 @
1B
#200000000
0!
0#
0+
0?
0B
#205000000
1!
1#
b00010001 %
1+
b00010001 -
b00010001 3
1?
b00010001 @
1B
#210000000
0!
0#
0+
0?
0B
#215000000
1!
1#
b00010010 %
1+
b00010010 -
b00010010 3
1?
b00010010 @
1B
#220000000
0!
0#
0+
0?
0B
#225000000
1!
1#
b00010011 %
1+
b00010011 -
b00010011 3
1?
b00010011 @
1B
#230000000
0!
0#
0+
0?
0B
#235000000
1!
1#
b00010100 %
1+
b00010100 -
b00010100 3
1?
b00010100 @
1B
#240000000
0!
1"
0#
1$
b00000000 %
0+
1,
b00000000 -
b00000000 3
0?
b00000000 @
0B
#245000000
1!
1#
b00000000000000110000001000000000 &
b00000101 '
b00000010 (
1+
b00000000000000110000001000000000 .
b00000101 /
b00000010 0
b00000000000000110000001000000000 4
b00000011 5
b00000010 6
b00000101 7
09
b00000011 :
b00000010 ;
b00000101 =
0>
1?
b00000000000000110000001000000000 A
1B
b00000101 C
b00000010 D
#250000000
0!
0#
0+
0?
0B
#255000000
1!
1#
b00000010 )
1+
b00000010 1
1?
1B
b00000010 E
#260000000
0!
0"
0#
0$
0+
0,
0?
0B
#265000000
1!
1#
b00000001 %
1+
b00000001 -
b00000001 3
1?
b00000001 @
1B
#270000000
0!
0#
0+
0?
0B
#275000000
1!
1#
b00000010 %
b00100000000001000000001100000000 &
b00000001 '
b00000011 (
0*
1+
b00000010 -
b00100000000001000000001100000000 .
b00000001 /
b00000011 0
02
b00000010 3
b00100000000001000000001100000000 4
b00000100 5
b00000011 6
b00000001 7
b001 8
b00000100 :
b00000011 ;
b001 <
b00000001 =
1?
b00000010 @
b00100000000001000000001100000000 A
1B
b00000001 C
b00000011 D
0F
#280000000
0!
0#
0+
0?
0B
#285000000
1!
1#
b00000011 %
b01000000000001010000010000000000 &
b00000100 '
b00000100 (
b00000000 )
1+
b00000011 -
b01000000000001010000010000000000 .
b00000100 /
b00000100 0
b00000000 1
b00000011 3
b01000000000001010000010000000000 4
b00000101 5
b00000100 6
b00000100 7
b010 8
b00000101 :
b00000100 ;
b010 <
b00000100 =
1?
b00000011 @
b01000000000001010000010000000000 A
1B
b00000100 C
b00000100 D
b00000000 E
#290000000
0!
0#
0+
0?
0B
#295000000
1!
1#
b00000100 %
b01100000000001100000010100000000 &
b00000111 '
b00000101 (
1+
b00000100 -
b01100000000001100000010100000000 .
b00000111 /
b00000101 0
b00000100 3
b01100000000001100000010100000000 4
b00000110 5
b00000101 6
b00000111 7
b011 8
b00000110 :
b00000101 ;
b011 <
b00000111 =
1?
b00000100 @
b01100000000001100000010100000000 A
1B
b00000111 C
b00000101 D
#300000000
0!
0#
0+
0?
0B
#305000000
1!
1#
b00000101 %
b10000000000001110000011000000000 &
b00000001 '
b00000110 (
1+
b00000101 -
b10000000000001110000011000000000 .
b00000001 /
b00000110 0
b00000101 3
b10000000000001110000011000000000 4
b00000111 5
b00000110 6
b00000001 7
b100 8
b00000111 :
b00000110 ;
b100 <
b00000001 =
1?
b00000101 @
b10000000000001110000011000000000 A
1B
b00000001 C
b00000110 D
#310000000
0!
0#
0+
0?
0B
#315000000
1!
1#
b00000110 %
b10100000000010000000011100000000 &
b11110000 '
b00000111 (
1+
b00000110 -
b10100000000010000000011100000000 .
b11110000 /
b00000111 0
b00000110 3
b10100000000010000000011100000000 4
b00001000 5
b00000111 6
b11110000 7
b101 8
b00001000 :
b00000111 ;
b101 <
b11110000 =
1?
b00000110 @
b10100000000010000000011100000000 A
1B
b11110000 C
b00000111 D
#320000000
0!
0#
0+
0?
0B
#325000000
1!
1#
b00000111 %
b00000000000000000000000000000000 &
b00000000 '
b00000000 (
1*
1+
b00000111 -
b00000000000000000000000000000000 .
b00000000 /
b00000000 0
12
b00000111 3
b00000000000000000000000000000000 4
b00000000 5
b00000000 6
b00000000 7
b000 8
19
b00000000 :
b00000000 ;
b000 <
b00000000 =
1>
1?
b00000111 @
b00000000000000000000000000000000 A
1B
b00000000 C
b00000000 D
1F
#330000000
0!
0#
0+
0?
0B
#335000000
1!
1#
b00001000 %
1+
b00001000 -
b00001000 3
1?
b00001000 @
1B
#340000000
0!
0#
0+
0?
0B
#345000000
1!
1#
b00001001 %
1+
b00001001 -
b00001001 3
1?
b00001001 @
1B
#350000000
0!
0#
0+
0?
0B
#355000000
1!
1#
b00001010 %
1+
b00001010 -
b00001010 3
1?
b00001010 @
1B
#360000000
0!
0#
0+
0?
0B
#365000000
1!
1#
b00001011 %
1+
b00001011 -
b00001011 3
1?
b00001011 @
1B
#370000000
0!
0#
0+
0?
0B
#375000000
1!
1#
b00001100 %
1+
b00001100 -
b00001100 3
1?
b00001100 @
1B
#380000000
0!
0#
0+
0?
0B
#385000000
1!
1#
b00001101 %
1+
b00001101 -
b00001101 3
1?
b00001101 @
1B
#390000000
0!
0#
0+
0?
0B
#395000000
1!
1#
b00001110 %
1+
b00001110 -
b00001110 3
1?
b00001110 @
1B
#400000000
0!
0#
0+
0?
0B
#405000000
1!
1#
b00001111 %
1+
b00001111 -
b00001111 3
1?
b00001111 @
1B
#410000000
0!
0#
0+
0?
0B
#415000000
1!
1#
b00010000 %
1+
b00010000 -
b00010000 3
1?
b00010000 @
1B
#420000000
0!
0#
0+
0?
0B
#425000000
1!
1#
b00010001 %
1+
b00010001 -
b00010001 3
1?
b00010001 @
1B
#430000000
0!
0#
0+
0?
0B
#435000000
1!
1#
b00010010 %
1+
b00010010 -
b00010010 3
1?
b00010010 @
1B
#440000000
0!
0#
0+
0?
0B
#445000000
1!
1#
b00010011 %
1+
b00010011 -
b00010011 3
1?
b00010011 @
1B
#450000000
0!
0#
0+
0?
0B
#455000000
1!
1#
b00010100 %
1+
b00010100 -
b00010100 3
1?
b00010100 @
1B
#460000000
0!
0#
0+
0?
0B
#465000000
1!
1#
b00010101 %
1+
b00010101 -
b00010101 3
1?
b00010101 @
1B
#470000000
0!
0#
0+
0?
0B
#475000000
1!
1#
b00010110 %
1+
b00010110 -
b00010110 3
1?
b00010110 @
1B
#480000000
0!
0#
0+
0?
0B
#485000000
1!
1#
b00010111 %
1+
b00010111 -
b00010111 3
1?
b00010111 @
1B
#490000000
0!
0#
0+
0?
0B
#495000000
1!
1#
b00011000 %
1+
b00011000 -
b00011000 3
1?
b00011000 @
1B
